odoo/addons/shopinvader_backend_image_proxy/README.rst
odoo/addons/shopinvader_backend_image_proxy/__init__.py
odoo/addons/shopinvader_backend_image_proxy/__manifest__.py
odoo/addons/shopinvader_backend_image_proxy/i18n/shopinvader_backend_image_proxy.pot
odoo/addons/shopinvader_backend_image_proxy/models/__init__.py
odoo/addons/shopinvader_backend_image_proxy/models/shopinvader_backend.py
odoo/addons/shopinvader_backend_image_proxy/models/shopinvader_image_mixin.py
odoo/addons/shopinvader_backend_image_proxy/readme/CONFIGURE.rst
odoo/addons/shopinvader_backend_image_proxy/readme/CONTRIBUTORS.rst
odoo/addons/shopinvader_backend_image_proxy/readme/DESCRIPTION.rst
odoo/addons/shopinvader_backend_image_proxy/static/description/index.html
odoo/addons/shopinvader_backend_image_proxy/tests/__init__.py
odoo/addons/shopinvader_backend_image_proxy/tests/test_shopinvader_backend.py
odoo/addons/shopinvader_backend_image_proxy/tests/test_shopinvader_image_mixin.py
odoo/addons/shopinvader_backend_image_proxy/views/shopinvader_backend.xml
odoo14_addon_shopinvader_backend_image_proxy-14.0.1.0.2.dist-info/METADATA
odoo14_addon_shopinvader_backend_image_proxy-14.0.1.0.2.dist-info/WHEEL
odoo14_addon_shopinvader_backend_image_proxy-14.0.1.0.2.dist-info/top_level.txt
odoo14_addon_shopinvader_backend_image_proxy-14.0.1.0.2.dist-info/RECORD
