Metadata-Version: 2.1
Name: odoo14-addon-shopinvader-backend-image-proxy
Version: 14.0.1.0.2
Summary: Add possibility to replace the image URL by the proxy url set on the SE backend
Home-page: https://github.com/shopinvader/odoo-shopinvader
Author: Akretion,ACSONE SA/NV
License: AGPL-3
Platform: UNKNOWN
Classifier: Programming Language :: Python
Classifier: Framework :: Odoo
Classifier: Framework :: Odoo :: 14.0
Classifier: License :: OSI Approved :: GNU Affero General Public License v3
Requires-Python: >=3.6
Requires-Dist: odoo14-addon-shopinvader-image
Requires-Dist: odoo (<14.1dev,>=14.0a)
